pysecp256k1/__init__.py
pysecp256k1/ecdh.py
pysecp256k1/extrakeys.py
pysecp256k1/recovery.py
pysecp256k1/schnorrsig.py
pysecp256k1/low_level/__init__.py
pysecp256k1/low_level/constants.py
pysecp256k1/low_level/secp256k1.py
pysecp256k1/low_level/util.py
python_secp256k1-0.3.0.dist-info/LICENSE
python_secp256k1-0.3.0.dist-info/METADATA
python_secp256k1-0.3.0.dist-info/WHEEL
python_secp256k1-0.3.0.dist-info/top_level.txt
python_secp256k1-0.3.0.dist-info/RECORD
