Metadata-Version: 2.1
Name: python-secp256k1
Version: 0.3.0
Summary: Ctypes Python3 FFI bindings for libsecp256k1
Home-page: https://github.com/scgbckbone/python-secp256k1
Author: scg
Author-email: scgbckbone@proton.me
License: MIT
Keywords: bitcoin,secp256k1,ecdsa,schnorr
Classifier: Programming Language :: Python :: 3.6
Classifier: Programming Language :: Python :: 3.7
Classifier: Programming Language :: Python :: 3.8
Classifier: Programming Language :: Python :: 3.9
Classifier: Programming Language :: Python :: 3.10
Classifier: License :: OSI Approved :: MIT License
Classifier: Natural Language :: English
License-File: LICENSE
Provides-Extra: typing_extensions
Requires-Dist: typing-extensions >=3.6 ; extra == 'typing_extensions'
